README.txt
setup.cfg
setup.py
Products/__init__.py
Products.HaufeWingDBG.egg-info/PKG-INFO
Products.HaufeWingDBG.egg-info/SOURCES.txt
Products.HaufeWingDBG.egg-info/dependency_links.txt
Products.HaufeWingDBG.egg-info/entry_points.txt
Products.HaufeWingDBG.egg-info/namespace_packages.txt
Products.HaufeWingDBG.egg-info/not-zip-safe
Products.HaufeWingDBG.egg-info/requires.txt
Products.HaufeWingDBG.egg-info/top_level.txt
Products/HaufeWingDBG/DebugHttpServer.py
Products/HaufeWingDBG/ScriptDebugging.py
Products/HaufeWingDBG/ScriptDebugging.py.orig
Products/HaufeWingDBG/TODO.txt
Products/HaufeWingDBG/WingDBG.py
Products/HaufeWingDBG/ZopeLogFile.py
Products/HaufeWingDBG/__init__.py
Products/HaufeWingDBG/config.py
Products/HaufeWingDBG/utils.py
Products/HaufeWingDBG/documentation/wingdbgdocs.html
Products/HaufeWingDBG/www/advanced.pt
Products/HaufeWingDBG/www/configure.pt
Products/HaufeWingDBG/www/connection_trouble_help.pt
Products/HaufeWingDBG/www/documentation.pt
Products/HaufeWingDBG/www/icon.gif
Products/HaufeWingDBG/www/migrate.pt
Products/HaufeWingDBG/www/remove.pt
Products/HaufeWingDBG/www/status.pt
docs/HISTORY.txt