Metadata-Version: 1.1
Name: Products.HaufeWingDBG
Version: 4.1.9
Summary: modified WingDBG product, as workaround for TrustedFSPythonScript debugging problem
Home-page: http://www.haufe.de/
Author: Peter Frey
Author-email: peter.frey@haufe.de
License: GPL
Platform: UNKNOWN
Classifier: Programming Language :: Python
Classifier: Topic :: Software Development :: Libraries :: Python Modules
